examples/__init__.py
examples/mnist_dataset.py
examples/simple_classifier.py
ride/__init__.py
ride/core.py
ride/feature_extraction.py
ride/feature_visualisation.py
ride/finetune.py
ride/hparamsearch.py
ride/info.py
ride/lifecycle.py
ride/logging.py
ride/main.py
ride/metrics.py
ride/optimizers.py
ride/runner.py
ride/unfreeze.py
ride/utils/__init__.py
ride/utils/checkpoints.py
ride/utils/discriminative_lr.py
ride/utils/env.py
ride/utils/gpus.py
ride/utils/io.py
ride/utils/logging.py
ride/utils/utils.py
tests/__init__.py
tests/dummy_dataset.py
tests/test_core.py
tests/test_examples.py
tests/test_feature_extraction.py
tests/test_feature_visualisation.py
tests/test_finetune.py
tests/test_info.py
tests/test_main.py
tests/test_metrics.py
tests/test_optimizers.py
tests/test_runner.py
tests/utils/__init__.py
tests/utils/test_io.py
tests/utils/test_utils.py
ride-0.7.2.dist-info/LICENSE
ride-0.7.2.dist-info/METADATA
ride-0.7.2.dist-info/WHEEL
ride-0.7.2.dist-info/top_level.txt
ride-0.7.2.dist-info/RECORD
