Metadata-Version: 2.1
Name: ride
Version: 0.7.2
Summary: Training wheels, side rails, and helicopter parent for your Deep Learning projects using Pytorch
Home-page: https://github.com/LukasHedegaard/ride
Author: Lukas Hedegaard
Author-email: lukasxhedegaard@gmail.com
License: UNKNOWN
Keywords: deep learning,pytorch,AI
Platform: UNKNOWN
Classifier: Environment :: Console
Classifier: Natural Language :: English
Classifier: Development Status :: 4 - Beta
Classifier: Intended Audience :: Developers
Classifier: Topic :: Scientific/Engineering :: Artificial Intelligence
Classifier: Topic :: Scientific/Engineering :: Image Recognition
Classifier: Topic :: Scientific/Engineering :: Information Analysis
Classifier: License :: OSI Approved :: Apache Software License
Classifier: Operating System :: OS Independent
Classifier: Programming Language :: Python :: 3.6
Classifier: Programming Language :: Python :: 3.7
Classifier: Programming Language :: Python :: 3.8
Classifier: Programming Language :: Python :: 3.9
Requires-Dist: corider
Requires-Dist: torchmetrics (<0.7,>=0.4)
Requires-Dist: pytorch-lightning (<1.5,>=1.3)
Requires-Dist: python-dotenv
Requires-Dist: supers (>=0.2)
Requires-Dist: matplotlib
Requires-Dist: seaborn
Requires-Dist: coloredlogs
Requires-Dist: gputil (>=1.4)
Requires-Dist: py-cpuinfo (>=7.0)
Requires-Dist: ptflops (>=0.6)
Requires-Dist: joblib (>=1.0)
Requires-Dist: psutil
Requires-Dist: pytorch-benchmark
Provides-Extra: build
Requires-Dist: protobuf (<=3.20) ; extra == 'build'
Requires-Dist: setuptools ; extra == 'build'
Requires-Dist: wheel ; extra == 'build'
Requires-Dist: twine ; extra == 'build'
Provides-Extra: dev
Requires-Dist: wandb (>=0.12.11) ; extra == 'dev'
Requires-Dist: flake8 ; extra == 'dev'
Requires-Dist: mypy ; extra == 'dev'
Requires-Dist: black ; extra == 'dev'
Requires-Dist: isort (>=5.7) ; extra == 'dev'
Requires-Dist: flake8-black ; extra == 'dev'
Requires-Dist: pytest (~=6.2.0) ; extra == 'dev'
Requires-Dist: pytest-order ; extra == 'dev'
Requires-Dist: pytest-cov ; extra == 'dev'
Requires-Dist: pytest-xdist ; extra == 'dev'
Requires-Dist: scikit-learn ; extra == 'dev'
Requires-Dist: umap-learn ; extra == 'dev'
Requires-Dist: ray[tune] (<2.0,>=1.2) ; extra == 'dev'
Requires-Dist: torchvision ; extra == 'dev'
Requires-Dist: lightning-bolts ; extra == 'dev'
Requires-Dist: redis ; (sys_platform == "win32") and extra == 'dev'
Provides-Extra: docs
Requires-Dist: sphinx (>=3.0) ; extra == 'docs'
Requires-Dist: nbsphinx (>=0.8) ; extra == 'docs'
Requires-Dist: pandoc (>=1.0) ; extra == 'docs'
Requires-Dist: docutils (>=0.16) ; extra == 'docs'
Requires-Dist: sphinxcontrib-fulltoc (>=1.0) ; extra == 'docs'
Requires-Dist: sphinxcontrib-mockautodoc ; extra == 'docs'
Requires-Dist: sphinx-autodoc-typehints (>=1.0) ; extra == 'docs'
Requires-Dist: sphinx-paramlinks (>=0.4.0) ; extra == 'docs'
Requires-Dist: sphinx-togglebutton (>=0.2) ; extra == 'docs'
Requires-Dist: sphinx-copybutton (>=0.3) ; extra == 'docs'
Requires-Dist: sphinx-autoapi (>=1.7) ; extra == 'docs'
Requires-Dist: m2r2 (>=0.2) ; extra == 'docs'
Provides-Extra: extras
Requires-Dist: lightning-bolts (==0.4) ; extra == 'extras'
Requires-Dist: ray[tune] (<2.0,>=1.2) ; extra == 'extras'
Requires-Dist: scikit-learn ; extra == 'extras'
Requires-Dist: torchvision ; extra == 'extras'
Requires-Dist: umap-learn ; extra == 'extras'
